quick_flask_server.py
quick_flask_server-1.1.2.dist-info/LICENSE
quick_flask_server-1.1.2.dist-info/METADATA
quick_flask_server-1.1.2.dist-info/WHEEL
quick_flask_server-1.1.2.dist-info/top_level.txt
quick_flask_server-1.1.2.dist-info/RECORD
