Metadata-Version: 2.1
Name: quick-flask-server
Version: 1.1.2
Summary: Quickly serve your flask apps using ngrok
Home-page: https://github.com/abhinand5/quick-flask-server.git
Author: Abhinand Balachandran
License: UNKNOWN
Keywords: flask ngrok server utility
Platform: UNKNOWN
Classifier: Programming Language :: Python :: 3.6
Classifier: License :: OSI Approved :: Apache Software License
Classifier: Operating System :: OS Independent
Requires-Dist: Flask (>=0.8)
Requires-Dist: requests
